<?xml version="1.0" encoding="utf-8"?>
<doctrine-mapping xmlns="http://doctrine-project.org/schemas/orm/doctrine-mapping" xmlns:xsi="http://www.w3.org/2001/XMLSchema-instance" xsi:schemaLocation="http://doctrine-project.org/schemas/orm/doctrine-mapping http://doctrine-project.org/schemas/orm/doctrine-mapping.xsd">
  <entity name="Application\Entity\Db\Affectation" table="AFFECTATION">
    <indexes>
      <index name="IDX_79DEF33B7F29375B" columns="HISTORIQUE_ID"/>
      <index name="IDX_79DEF33B78FF2BCB" columns="INTERVENANT_ID"/>
      <index name="IDX_79DEF33B884B0F7B" columns="STRUCTURE_ID"/>
    </indexes>
    <id name="intervenant" association-key="true"/>
    <id name="structure" association-key="true"/>
    <field name="principale" type="boolean" column="PRINCIPALE" nullable="false"/>
    <field name="recherche" type="boolean" column="RECHERCHE" nullable="false"/>
    <one-to-one field="structure" target-entity="Application\Entity\Db\Structure">
      <join-columns>
        <join-column name="STRUCTURE_ID" referenced-column-name="ID"/>
      </join-columns>
    </one-to-one>
    <one-to-one field="intervenant" target-entity="Application\Entity\Db\Intervenant">
      <join-columns>
        <join-column name="INTERVENANT_ID" referenced-column-name="ID"/>
      </join-columns>
    </one-to-one>
    <many-to-one field="historique" target-entity="Application\Entity\Db\Historique">
      <join-columns>
        <join-column name="HISTORIQUE_ID" referenced-column-name="ID"/>
      </join-columns>
    </many-to-one>
  </entity>
</doctrine-mapping>
