<?xml version="1.0" encoding="utf-8"?>
<doctrine-mapping xmlns="http://doctrine-project.org/schemas/orm/doctrine-mapping"
                  xmlns:xsi="http://www.w3.org/2001/XMLSchema-instance"
                  xsi:schemaLocation="http://doctrine-project.org/schemas/orm/doctrine-mapping http://doctrine-project.org/schemas/orm/doctrine-mapping.xsd">
    <entity name="Service\Entity\Db\CampagneSaisie" table="CAMPAGNE_SAISIE">
        <id name="id" type="integer" column="ID">
            <generator strategy="SEQUENCE"/>
        </id>
        <field name="dateDebut" type="datetime" column="DATE_DEBUT" nullable="true"/>
        <field name="dateFin" type="datetime" column="DATE_FIN" nullable="true"/>
        <field name="messageIntervenant" type="string" column="MESSAGE_INTERVENANT" length="300" nullable="false"/>
        <field name="messageAutres" type="string" column="MESSAGE_AUTRES" length="300" nullable="false"/>
        <many-to-one field="annee" target-entity="Application\Entity\Db\Annee">
            <join-column name="ANNEE_ID" referenced-column-name="ID"/>
        </many-to-one>
        <many-to-one field="typeVolumeHoraire" target-entity="Service\Entity\Db\TypeVolumeHoraire">
            <join-column name="TYPE_VOLUME_HORAIRE_ID" referenced-column-name="ID"/>
        </many-to-one>
        <many-to-one field="typeIntervenant" target-entity="Intervenant\Entity\Db\TypeIntervenant">
            <join-column name="TYPE_INTERVENANT_ID" referenced-column-name="ID"/>
        </many-to-one>
    </entity>
</doctrine-mapping>